{
  "SPY": {
    "price": 754.24,
    "change_pct": -0.7,
    "name": "S&P 500 ETF",
    "_updated": "2026-06-05T06:21:54.854207+00:00"
  },
  "QQQ": {
    "price": 744.21,
    "change_pct": -0.26,
    "name": "Nasdaq 100 ETF",
    "_updated": "2026-06-05T06:21:54.854648+00:00"
  },
  "DIA": {
    "price": 508.26,
    "change_pct": -1.13,
    "name": "Dow Jones ETF",
    "_updated": "2026-06-05T06:21:54.855030+00:00"
  },
  "IWM": {
    "price": 287.67,
    "change_pct": -1.37,
    "name": "Russell 2000 ETF",
    "_updated": "2026-06-05T06:21:54.855445+00:00"
  },
  "AAPL": {
    "price": 310.26,
    "change_pct": -1.57,
    "name": "Apple",
    "_updated": "2026-06-05T06:21:54.855799+00:00"
  },
  "MSFT": {
    "price": 427.34,
    "change_pct": -3.17,
    "name": "Microsoft",
    "_updated": "2026-06-05T06:21:54.856142+00:00"
  },
  "GOOGL": {
    "price": 358.99,
    "change_pct": -0.79,
    "name": "Alphabet",
    "_updated": "2026-06-05T06:21:54.856510+00:00"
  },
  "AMZN": {
    "price": 250.02,
    "change_pct": -2.53,
    "name": "Amazon",
    "_updated": "2026-06-05T06:21:54.856886+00:00"
  },
  "META": {
    "price": 622.98,
    "change_pct": 4.24,
    "name": "Meta Platforms",
    "_updated": "2026-06-05T06:21:54.857246+00:00"
  },
  "NVDA": {
    "price": 214.75,
    "change_pct": -3.62,
    "name": "NVIDIA",
    "_updated": "2026-06-05T06:21:54.857582+00:00"
  },
  "TSLA": {
    "price": 423.7,
    "change_pct": -0.01,
    "name": "Tesla",
    "_updated": "2026-06-05T06:21:54.857905+00:00"
  },
  "JPM": {
    "price": 300.85,
    "change_pct": -0.04,
    "name": "JPMorgan Chase",
    "_updated": "2026-06-05T06:21:54.858249+00:00"
  },
  "BAC": {
    "price": 52.4,
    "change_pct": -0.15,
    "name": "Bank of America",
    "_updated": "2026-06-05T06:21:54.858576+00:00"
  },
  "GS": {
    "price": 1041.02,
    "change_pct": -2.21,
    "name": "Goldman Sachs",
    "_updated": "2026-06-05T06:21:54.858892+00:00"
  },
  "XOM": {
    "price": 152.53,
    "change_pct": 1.99,
    "name": "ExxonMobil",
    "_updated": "2026-06-05T06:21:54.859227+00:00"
  },
  "CVX": {
    "price": 189.71,
    "change_pct": 1.15,
    "name": "Chevron",
    "_updated": "2026-06-05T06:21:54.859559+00:00"
  },
  "LMT": {
    "price": 512.03,
    "change_pct": -0.27,
    "name": "Lockheed Martin",
    "_updated": "2026-06-05T06:21:54.859900+00:00"
  },
  "RTX": {
    "price": 172.55,
    "change_pct": -0.98,
    "name": "RTX Corp",
    "_updated": "2026-06-05T06:21:54.860238+00:00"
  },
  "NOC": {
    "price": 526.06,
    "change_pct": -1.96,
    "name": "Northrop Grumman",
    "_updated": "2026-06-05T06:21:54.860563+00:00"
  },
  "LLY": {
    "price": 1078.78,
    "change_pct": 1.37,
    "name": "Eli Lilly",
    "_updated": "2026-06-05T06:21:54.860879+00:00"
  },
  "PFE": {
    "price": 25.34,
    "change_pct": -0.82,
    "name": "Pfizer",
    "_updated": "2026-06-05T06:21:54.861238+00:00"
  },
  "JNJ": {
    "price": 223.24,
    "change_pct": 0.16,
    "name": "Johnson & Johnson",
    "_updated": "2026-06-05T06:21:54.861596+00:00"
  },
  "BTC": {
    "price": 61498.89,
    "change_pct": -3.93,
    "name": "Bitcoin",
    "_updated": "2026-06-05T06:21:54.861919+00:00"
  },
  "ETH": {
    "price": 1657.57,
    "change_pct": -8.51,
    "name": "Ethereum",
    "_updated": "2026-06-05T06:21:54.862255+00:00"
  },
  "GLD": {
    "price": 407.87,
    "change_pct": -0.99,
    "name": "Gold ETF",
    "_updated": "2026-06-05T06:21:54.862583+00:00"
  },
  "TLT": {
    "price": 85.31,
    "change_pct": -0.4,
    "name": "20yr Treasury ETF",
    "_updated": "2026-06-05T06:21:54.862893+00:00"
  },
  "PLTR": {
    "price": 142.2,
    "change_pct": -6.55,
    "name": "Palantir",
    "_updated": "2026-06-05T06:21:54.863222+00:00"
  },
  "COIN": {
    "price": 163.22,
    "change_pct": -6.19,
    "name": "Coinbase",
    "_updated": "2026-06-05T06:21:54.863541+00:00"
  },
  "RSVRW": {
    "price": 0.137,
    "change_pct": 1.48,
    "name": "RSVRW",
    "_updated": "2026-06-05T06:21:54.863847+00:00"
  },
  "AGL": {
    "price": 82.7,
    "change_pct": -4.67,
    "name": "AGL",
    "_updated": "2026-06-05T06:21:54.864152+00:00"
  },
  "GCT": {
    "price": 32.41,
    "change_pct": -6.03,
    "name": "GCT",
    "_updated": "2026-06-05T06:21:54.864501+00:00"
  },
  "UNH": {
    "price": 377.0,
    "change_pct": -0.24,
    "name": "UnitedHealth Group",
    "_updated": "2026-06-05T06:21:54.864816+00:00"
  },
  "HCA": {
    "price": 363.23,
    "change_pct": -1.12,
    "name": "HCA Healthcare",
    "_updated": "2026-06-05T06:21:54.865126+00:00"
  },
  "CVS": {
    "price": 91.37,
    "change_pct": 2.09,
    "name": "CVS Health",
    "_updated": "2026-06-05T06:21:54.865560+00:00"
  },
  "XRP": {
    "price": 1.1,
    "change_pct": -8.23,
    "name": "XRP Ripple",
    "_updated": "2026-06-05T06:21:54.865875+00:00"
  },
  "XLF": {
    "price": 50.87,
    "change_pct": -1.15,
    "name": "Financial ETF",
    "_updated": "2026-06-05T06:21:54.866205+00:00"
  }
}