{
  "SPY": {
    "price": 741.0,
    "change_pct": 1.65,
    "name": "S&P 500 ETF",
    "_updated": "2026-06-29T22:37:07.714209+00:00"
  },
  "QQQ": {
    "price": 724.08,
    "change_pct": 2.49,
    "name": "Nasdaq 100 ETF",
    "_updated": "2026-06-29T22:37:07.714679+00:00"
  },
  "DIA": {
    "price": 521.68,
    "change_pct": 0.76,
    "name": "Dow Jones ETF",
    "_updated": "2026-06-29T22:37:07.715169+00:00"
  },
  "IWM": {
    "price": 298.97,
    "change_pct": -0.29,
    "name": "Russell 2000 ETF",
    "_updated": "2026-06-29T22:37:07.715632+00:00"
  },
  "AAPL": {
    "price": 281.74,
    "change_pct": -0.72,
    "name": "Apple",
    "_updated": "2026-06-29T22:37:07.716102+00:00"
  },
  "MSFT": {
    "price": 368.57,
    "change_pct": -1.18,
    "name": "Microsoft",
    "_updated": "2026-06-29T22:37:07.716530+00:00"
  },
  "GOOGL": {
    "price": 353.65,
    "change_pct": 4.82,
    "name": "Alphabet",
    "_updated": "2026-06-29T22:37:07.716977+00:00"
  },
  "AMZN": {
    "price": 240.14,
    "change_pct": 3.2,
    "name": "Amazon",
    "_updated": "2026-06-29T22:37:07.717500+00:00"
  },
  "META": {
    "price": 562.6,
    "change_pct": 2.24,
    "name": "Meta Platforms",
    "_updated": "2026-06-29T22:37:07.717960+00:00"
  },
  "NVDA": {
    "price": 194.97,
    "change_pct": 1.27,
    "name": "NVIDIA",
    "_updated": "2026-06-29T22:37:07.718372+00:00"
  },
  "TSLA": {
    "price": 411.84,
    "change_pct": 8.46,
    "name": "Tesla",
    "_updated": "2026-06-29T22:37:07.718884+00:00"
  },
  "JPM": {
    "price": 329.39,
    "change_pct": 0.1,
    "name": "JPMorgan Chase",
    "_updated": "2026-06-29T22:37:07.719300+00:00"
  },
  "BAC": {
    "price": 57.88,
    "change_pct": 0.0,
    "name": "Bank of America",
    "_updated": "2026-06-29T22:37:07.719705+00:00"
  },
  "GS": {
    "price": 1020.21,
    "change_pct": 0.06,
    "name": "Goldman Sachs",
    "_updated": "2026-06-29T22:37:07.720136+00:00"
  },
  "XOM": {
    "price": 136.06,
    "change_pct": -0.35,
    "name": "ExxonMobil",
    "_updated": "2026-06-29T22:37:07.720536+00:00"
  },
  "CVX": {
    "price": 168.47,
    "change_pct": -1.51,
    "name": "Chevron",
    "_updated": "2026-06-29T22:37:07.720970+00:00"
  },
  "LMT": {
    "price": 502.07,
    "change_pct": -1.05,
    "name": "Lockheed Martin",
    "_updated": "2026-06-29T22:37:07.721375+00:00"
  },
  "RTX": {
    "price": 187.33,
    "change_pct": -0.35,
    "name": "RTX Corp",
    "_updated": "2026-06-29T22:37:07.721800+00:00"
  },
  "NOC": {
    "price": 496.02,
    "change_pct": -0.8,
    "name": "Northrop Grumman",
    "_updated": "2026-06-29T22:37:07.722211+00:00"
  },
  "LLY": {
    "price": 1229.93,
    "change_pct": 1.81,
    "name": "Eli Lilly",
    "_updated": "2026-06-29T22:37:07.722610+00:00"
  },
  "PFE": {
    "price": 24.37,
    "change_pct": 0.33,
    "name": "Pfizer",
    "_updated": "2026-06-29T22:37:07.723043+00:00"
  },
  "JNJ": {
    "price": 258.51,
    "change_pct": 1.51,
    "name": "Johnson & Johnson",
    "_updated": "2026-06-29T22:37:07.723440+00:00"
  },
  "BTC": {
    "price": 60268.88,
    "change_pct": 1.24,
    "name": "Bitcoin",
    "_updated": "2026-06-29T22:37:07.723868+00:00"
  },
  "ETH": {
    "price": 1611.97,
    "change_pct": 2.65,
    "name": "Ethereum",
    "_updated": "2026-06-29T22:37:07.724276+00:00"
  },
  "GLD": {
    "price": 368.58,
    "change_pct": -1.35,
    "name": "Gold ETF",
    "_updated": "2026-06-29T22:37:07.724671+00:00"
  },
  "TLT": {
    "price": 87.45,
    "change_pct": 0.1,
    "name": "20yr Treasury ETF",
    "_updated": "2026-06-29T22:37:07.725092+00:00"
  },
  "PLTR": {
    "price": 115.7,
    "change_pct": 2.45,
    "name": "Palantir",
    "_updated": "2026-06-29T22:37:07.725485+00:00"
  },
  "COIN": {
    "price": 151.65,
    "change_pct": 1.74,
    "name": "Coinbase",
    "_updated": "2026-06-29T22:37:07.725914+00:00"
  },
  "ACDC": {
    "price": 5.8,
    "change_pct": -0.51,
    "name": "ACDC",
    "_updated": "2026-06-29T22:37:07.726312+00:00"
  },
  "GWRE": {
    "price": 120.87,
    "change_pct": -0.5,
    "name": "GWRE",
    "_updated": "2026-06-29T22:37:07.726706+00:00"
  },
  "NWN": {
    "price": 49.98,
    "change_pct": -1.67,
    "name": "NWN",
    "_updated": "2026-06-29T22:37:07.727136+00:00"
  },
  "BFST": {
    "price": 30.67,
    "change_pct": -0.45,
    "name": "BFST",
    "_updated": "2026-06-29T22:37:07.727531+00:00"
  },
  "ROIV": {
    "price": 34.73,
    "change_pct": 1.94,
    "name": "ROIV",
    "_updated": "2026-06-29T22:37:07.727957+00:00"
  },
  "STRRP": {
    "price": 9.71,
    "change_pct": 0.51,
    "name": "STRRP",
    "_updated": "2026-06-29T22:37:07.728658+00:00"
  },
  "UNH": {
    "price": 419.82,
    "change_pct": -1.89,
    "name": "UnitedHealth Group",
    "_updated": "2026-06-29T22:37:07.729092+00:00"
  },
  "HCA": {
    "price": 392.33,
    "change_pct": 0.17,
    "name": "HCA Healthcare",
    "_updated": "2026-06-29T22:37:07.729489+00:00"
  },
  "CVS": {
    "price": 103.58,
    "change_pct": -0.73,
    "name": "CVS Health",
    "_updated": "2026-06-29T22:37:07.729909+00:00"
  },
  "XLF": {
    "price": 53.72,
    "change_pct": 0.28,
    "name": "Financial ETF",
    "_updated": "2026-06-29T22:37:07.730311+00:00"
  },
  "MRK": {
    "price": 129.38,
    "change_pct": 0.56,
    "name": "Merck",
    "_updated": "2026-06-29T22:37:07.730708+00:00"
  },
  "CORN": {
    "price": 16.47,
    "change_pct": -2.31,
    "name": "Corn ETF",
    "_updated": "2026-06-29T22:37:07.731136+00:00"
  },
  "SOYB": {
    "price": 24.22,
    "change_pct": -1.14,
    "name": "Soybean ETF",
    "_updated": "2026-06-29T22:37:07.731530+00:00"
  },
  "DE": {
    "price": 626.63,
    "change_pct": 2.18,
    "name": "Deere & Company",
    "_updated": "2026-06-29T22:37:07.731957+00:00"
  },
  "XRP": {
    "price": 1.06,
    "change_pct": 1.07,
    "name": "XRP Ripple",
    "_updated": "2026-06-29T22:37:07.732354+00:00"
  }
}