{
  "SPY": {
    "price": 739.22,
    "change_pct": 0.23,
    "name": "S&P 500 ETF",
    "_updated": "2026-06-09T01:46:16.633679+00:00"
  },
  "QQQ": {
    "price": 716.07,
    "change_pct": 1.56,
    "name": "Nasdaq 100 ETF",
    "_updated": "2026-06-09T01:46:16.634164+00:00"
  },
  "DIA": {
    "price": 508.91,
    "change_pct": -0.15,
    "name": "Dow Jones ETF",
    "_updated": "2026-06-09T01:46:16.634652+00:00"
  },
  "IWM": {
    "price": 284.11,
    "change_pct": 0.87,
    "name": "Russell 2000 ETF",
    "_updated": "2026-06-09T01:46:16.635104+00:00"
  },
  "AAPL": {
    "price": 301.54,
    "change_pct": -1.89,
    "name": "Apple",
    "_updated": "2026-06-09T01:46:16.635565+00:00"
  },
  "MSFT": {
    "price": 411.74,
    "change_pct": -1.18,
    "name": "Microsoft",
    "_updated": "2026-06-09T01:46:16.635987+00:00"
  },
  "GOOGL": {
    "price": 363.31,
    "change_pct": -1.36,
    "name": "Alphabet",
    "_updated": "2026-06-09T01:46:16.636412+00:00"
  },
  "AMZN": {
    "price": 245.22,
    "change_pct": -0.33,
    "name": "Amazon",
    "_updated": "2026-06-09T01:46:16.636888+00:00"
  },
  "META": {
    "price": 585.39,
    "change_pct": -1.28,
    "name": "Meta Platforms",
    "_updated": "2026-06-09T01:46:16.637301+00:00"
  },
  "NVDA": {
    "price": 208.64,
    "change_pct": 1.73,
    "name": "NVIDIA",
    "_updated": "2026-06-09T01:46:16.637739+00:00"
  },
  "TSLA": {
    "price": 408.95,
    "change_pct": 4.59,
    "name": "Tesla",
    "_updated": "2026-06-09T01:46:16.638144+00:00"
  },
  "JPM": {
    "price": 311.11,
    "change_pct": -0.4,
    "name": "JPMorgan Chase",
    "_updated": "2026-06-09T01:46:16.638577+00:00"
  },
  "BAC": {
    "price": 53.63,
    "change_pct": -0.37,
    "name": "Bank of America",
    "_updated": "2026-06-09T01:46:16.638979+00:00"
  },
  "GS": {
    "price": 1045.0,
    "change_pct": 0.61,
    "name": "Goldman Sachs",
    "_updated": "2026-06-09T01:46:16.639381+00:00"
  },
  "XOM": {
    "price": 151.75,
    "change_pct": 1.22,
    "name": "ExxonMobil",
    "_updated": "2026-06-09T01:46:16.639816+00:00"
  },
  "CVX": {
    "price": 189.24,
    "change_pct": 1.03,
    "name": "Chevron",
    "_updated": "2026-06-09T01:46:16.640219+00:00"
  },
  "LMT": {
    "price": 520.07,
    "change_pct": -0.7,
    "name": "Lockheed Martin",
    "_updated": "2026-06-09T01:46:16.640654+00:00"
  },
  "RTX": {
    "price": 178.66,
    "change_pct": -1.29,
    "name": "RTX Corp",
    "_updated": "2026-06-09T01:46:16.641058+00:00"
  },
  "NOC": {
    "price": 540.81,
    "change_pct": -0.66,
    "name": "Northrop Grumman",
    "_updated": "2026-06-09T01:46:16.641489+00:00"
  },
  "LLY": {
    "price": 1149.15,
    "change_pct": 1.57,
    "name": "Eli Lilly",
    "_updated": "2026-06-09T01:46:16.641893+00:00"
  },
  "PFE": {
    "price": 25.62,
    "change_pct": -1.61,
    "name": "Pfizer",
    "_updated": "2026-06-09T01:46:16.642295+00:00"
  },
  "JNJ": {
    "price": 232.16,
    "change_pct": -0.26,
    "name": "Johnson & Johnson",
    "_updated": "2026-06-09T01:46:16.642722+00:00"
  },
  "BTC": {
    "price": 62710.7,
    "change_pct": -0.84,
    "name": "Bitcoin",
    "_updated": "2026-06-09T01:46:16.643127+00:00"
  },
  "ETH": {
    "price": 1669.05,
    "change_pct": -1.03,
    "name": "Ethereum",
    "_updated": "2026-06-09T01:46:16.643556+00:00"
  },
  "GLD": {
    "price": 397.27,
    "change_pct": 0.26,
    "name": "Gold ETF",
    "_updated": "2026-06-09T01:46:16.643961+00:00"
  },
  "TLT": {
    "price": 84.62,
    "change_pct": -0.52,
    "name": "20yr Treasury ETF",
    "_updated": "2026-06-09T01:46:16.644360+00:00"
  },
  "PLTR": {
    "price": 136.47,
    "change_pct": 0.69,
    "name": "Palantir",
    "_updated": "2026-06-09T01:46:16.644805+00:00"
  },
  "COIN": {
    "price": 162.11,
    "change_pct": 6.37,
    "name": "Coinbase",
    "_updated": "2026-06-09T01:46:16.645210+00:00"
  },
  "FCPT": {
    "price": 24.49,
    "change_pct": -0.85,
    "name": "FCPT",
    "_updated": "2026-06-09T01:46:16.645643+00:00"
  },
  "DELL": {
    "price": 400.77,
    "change_pct": 1.62,
    "name": "Dell",
    "_updated": "2026-06-09T01:46:16.646050+00:00"
  },
  "UNH": {
    "price": 406.57,
    "change_pct": 1.78,
    "name": "UnitedHealth Group",
    "_updated": "2026-06-09T01:46:16.646488+00:00"
  },
  "HCA": {
    "price": 361.32,
    "change_pct": -2.9,
    "name": "HCA Healthcare",
    "_updated": "2026-06-09T01:46:16.646897+00:00"
  },
  "CVS": {
    "price": 97.08,
    "change_pct": 1.2,
    "name": "CVS Health",
    "_updated": "2026-06-09T01:46:16.647300+00:00"
  },
  "AA": {
    "price": 73.44,
    "change_pct": 2.16,
    "name": "Alcoa",
    "_updated": "2026-06-09T01:46:16.648205+00:00"
  },
  "NUE": {
    "price": 253.4,
    "change_pct": -0.39,
    "name": "Nucor",
    "_updated": "2026-06-09T01:46:16.648642+00:00"
  },
  "XRP": {
    "price": 1.15,
    "change_pct": -0.26,
    "name": "XRP Ripple",
    "_updated": "2026-06-09T01:46:16.649044+00:00"
  },
  "XLF": {
    "price": 51.97,
    "change_pct": -0.63,
    "name": "Financial ETF",
    "_updated": "2026-06-09T01:46:16.649470+00:00"
  }
}