{
  "SPY": {
    "price": 737.55,
    "change_pct": -2.58,
    "name": "S&P 500 ETF",
    "_updated": "2026-06-07T18:58:14.565257+00:00"
  },
  "QQQ": {
    "price": 705.06,
    "change_pct": -4.8,
    "name": "Nasdaq 100 ETF",
    "_updated": "2026-06-07T18:58:14.565688+00:00"
  },
  "DIA": {
    "price": 509.7,
    "change_pct": -1.35,
    "name": "Dow Jones ETF",
    "_updated": "2026-06-07T18:58:14.566072+00:00"
  },
  "IWM": {
    "price": 281.65,
    "change_pct": -3.55,
    "name": "Russell 2000 ETF",
    "_updated": "2026-06-07T18:58:14.566454+00:00"
  },
  "AAPL": {
    "price": 307.34,
    "change_pct": -1.25,
    "name": "Apple",
    "_updated": "2026-06-07T18:58:14.566800+00:00"
  },
  "MSFT": {
    "price": 416.67,
    "change_pct": -2.66,
    "name": "Microsoft",
    "_updated": "2026-06-07T18:58:14.567138+00:00"
  },
  "GOOGL": {
    "price": 368.53,
    "change_pct": -0.98,
    "name": "Alphabet",
    "_updated": "2026-06-07T18:58:14.567485+00:00"
  },
  "AMZN": {
    "price": 246.03,
    "change_pct": -3.06,
    "name": "Amazon",
    "_updated": "2026-06-07T18:58:14.567842+00:00"
  },
  "META": {
    "price": 593.0,
    "change_pct": -5.51,
    "name": "Meta Platforms",
    "_updated": "2026-06-07T18:58:14.568173+00:00"
  },
  "NVDA": {
    "price": 205.1,
    "change_pct": -6.2,
    "name": "NVIDIA",
    "_updated": "2026-06-07T18:58:14.568553+00:00"
  },
  "TSLA": {
    "price": 391.0,
    "change_pct": -6.56,
    "name": "Tesla",
    "_updated": "2026-06-07T18:58:14.568894+00:00"
  },
  "JPM": {
    "price": 312.37,
    "change_pct": 0.48,
    "name": "JPMorgan Chase",
    "_updated": "2026-06-07T18:58:14.569218+00:00"
  },
  "BAC": {
    "price": 53.83,
    "change_pct": -0.11,
    "name": "Bank of America",
    "_updated": "2026-06-07T18:58:14.569563+00:00"
  },
  "GS": {
    "price": 1038.68,
    "change_pct": -4.94,
    "name": "Goldman Sachs",
    "_updated": "2026-06-07T18:58:14.569883+00:00"
  },
  "XOM": {
    "price": 149.92,
    "change_pct": -1.39,
    "name": "ExxonMobil",
    "_updated": "2026-06-07T18:58:14.570194+00:00"
  },
  "CVX": {
    "price": 187.31,
    "change_pct": -0.55,
    "name": "Chevron",
    "_updated": "2026-06-07T18:58:14.570527+00:00"
  },
  "LMT": {
    "price": 523.76,
    "change_pct": 0.91,
    "name": "Lockheed Martin",
    "_updated": "2026-06-07T18:58:14.570839+00:00"
  },
  "RTX": {
    "price": 180.99,
    "change_pct": 0.88,
    "name": "RTX Corp",
    "_updated": "2026-06-07T18:58:14.571143+00:00"
  },
  "NOC": {
    "price": 544.4,
    "change_pct": -0.14,
    "name": "Northrop Grumman",
    "_updated": "2026-06-07T18:58:14.571473+00:00"
  },
  "LLY": {
    "price": 1131.42,
    "change_pct": 0.55,
    "name": "Eli Lilly",
    "_updated": "2026-06-07T18:58:14.571791+00:00"
  },
  "PFE": {
    "price": 26.04,
    "change_pct": 1.36,
    "name": "Pfizer",
    "_updated": "2026-06-07T18:58:14.572100+00:00"
  },
  "JNJ": {
    "price": 232.77,
    "change_pct": 2.02,
    "name": "Johnson & Johnson",
    "_updated": "2026-06-07T18:58:14.572433+00:00"
  },
  "BTC": {
    "price": 62100.84,
    "change_pct": 2.03,
    "name": "Bitcoin",
    "_updated": "2026-06-07T18:58:14.572767+00:00"
  },
  "ETH": {
    "price": 1631.75,
    "change_pct": 4.01,
    "name": "Ethereum",
    "_updated": "2026-06-07T18:58:14.573073+00:00"
  },
  "GLD": {
    "price": 396.24,
    "change_pct": -3.65,
    "name": "Gold ETF",
    "_updated": "2026-06-07T18:58:14.573403+00:00"
  },
  "TLT": {
    "price": 85.06,
    "change_pct": -0.51,
    "name": "20yr Treasury ETF",
    "_updated": "2026-06-07T18:58:14.573722+00:00"
  },
  "PLTR": {
    "price": 135.53,
    "change_pct": -4.35,
    "name": "Palantir",
    "_updated": "2026-06-07T18:58:14.574027+00:00"
  },
  "COIN": {
    "price": 152.4,
    "change_pct": -7.15,
    "name": "Coinbase",
    "_updated": "2026-06-07T18:58:14.574348+00:00"
  },
  "UNH": {
    "price": 399.47,
    "change_pct": 0.76,
    "name": "UnitedHealth Group",
    "_updated": "2026-06-07T18:58:14.574685+00:00"
  },
  "HCA": {
    "price": 372.13,
    "change_pct": 2.85,
    "name": "HCA Healthcare",
    "_updated": "2026-06-07T18:58:14.574990+00:00"
  },
  "CVS": {
    "price": 95.93,
    "change_pct": 1.17,
    "name": "CVS Health",
    "_updated": "2026-06-07T18:58:14.575296+00:00"
  },
  "AA": {
    "price": 71.89,
    "change_pct": -7.86,
    "name": "Alcoa",
    "_updated": "2026-06-07T18:58:14.575901+00:00"
  },
  "NUE": {
    "price": 254.39,
    "change_pct": -3.01,
    "name": "Nucor",
    "_updated": "2026-06-07T18:58:14.576458+00:00"
  },
  "WHFCL": {
    "price": 25.3,
    "change_pct": -0.78,
    "name": "WHFCL",
    "_updated": "2026-06-07T18:58:14.576789+00:00"
  },
  "LNSR": {
    "price": 5.6,
    "change_pct": -0.36,
    "name": "LNSR",
    "_updated": "2026-06-07T18:58:14.577107+00:00"
  },
  "DK": {
    "price": 48.28,
    "change_pct": 1.28,
    "name": "DK",
    "_updated": "2026-06-07T18:58:14.577435+00:00"
  },
  "NTRA": {
    "price": 215.31,
    "change_pct": -3.06,
    "name": "NTRA",
    "_updated": "2026-06-07T18:58:14.577749+00:00"
  },
  "ACMR": {
    "price": 76.29,
    "change_pct": -15.43,
    "name": "ACMR",
    "_updated": "2026-06-07T18:58:14.578053+00:00"
  },
  "ATLX": {
    "price": 3.53,
    "change_pct": -16.35,
    "name": "ATLX",
    "_updated": "2026-06-07T18:58:14.578355+00:00"
  },
  "SITM": {
    "price": 625.68,
    "change_pct": -11.5,
    "name": "SITM",
    "_updated": "2026-06-07T18:58:14.578687+00:00"
  },
  "AVD": {
    "price": 2.66,
    "change_pct": 5.98,
    "name": "AVD",
    "_updated": "2026-06-07T18:58:14.579009+00:00"
  },
  "XRP": {
    "price": 1.14,
    "change_pct": 4.63,
    "name": "XRP Ripple",
    "_updated": "2026-06-07T18:58:14.579321+00:00"
  },
  "XLF": {
    "price": 52.3,
    "change_pct": 0.21,
    "name": "Financial ETF",
    "_updated": "2026-06-07T18:58:14.579655+00:00"
  }
}