{
  "SPY": {
    "price": 708.72,
    "change_pct": -0.2,
    "name": "S&P 500 ETF",
    "_updated": "2026-04-21T13:26:28.880011+00:00"
  },
  "QQQ": {
    "price": 646.79,
    "change_pct": -0.32,
    "name": "Nasdaq 100 ETF",
    "_updated": "2026-04-21T13:26:28.880507+00:00"
  },
  "DIA": {
    "price": 494.33,
    "change_pct": 0.02,
    "name": "Dow Jones ETF",
    "_updated": "2026-04-21T13:26:28.880968+00:00"
  },
  "IWM": {
    "price": 277.35,
    "change_pct": 0.57,
    "name": "Russell 2000 ETF",
    "_updated": "2026-04-21T13:26:28.881413+00:00"
  },
  "AAPL": {
    "price": 273.05,
    "change_pct": 1.04,
    "name": "Apple",
    "_updated": "2026-04-21T13:26:28.881869+00:00"
  },
  "MSFT": {
    "price": 418.07,
    "change_pct": -1.12,
    "name": "Microsoft",
    "_updated": "2026-04-21T13:26:28.882284+00:00"
  },
  "GOOGL": {
    "price": 337.42,
    "change_pct": -1.25,
    "name": "Alphabet",
    "_updated": "2026-04-21T13:26:28.882736+00:00"
  },
  "AMZN": {
    "price": 248.28,
    "change_pct": -0.91,
    "name": "Amazon",
    "_updated": "2026-04-21T13:26:28.883179+00:00"
  },
  "META": {
    "price": 670.91,
    "change_pct": -2.56,
    "name": "Meta Platforms",
    "_updated": "2026-04-21T13:26:28.883614+00:00"
  },
  "NVDA": {
    "price": 202.06,
    "change_pct": 0.19,
    "name": "NVIDIA",
    "_updated": "2026-04-21T13:26:28.884011+00:00"
  },
  "TSLA": {
    "price": 392.5,
    "change_pct": -2.03,
    "name": "Tesla",
    "_updated": "2026-04-21T13:26:28.884406+00:00"
  },
  "JPM": {
    "price": 316.99,
    "change_pct": 2.16,
    "name": "JPMorgan Chase",
    "_updated": "2026-04-21T13:26:28.884885+00:00"
  },
  "BAC": {
    "price": 53.95,
    "change_pct": 0.07,
    "name": "Bank of America",
    "_updated": "2026-04-21T13:26:28.885303+00:00"
  },
  "GS": {
    "price": 941.74,
    "change_pct": 1.71,
    "name": "Goldman Sachs",
    "_updated": "2026-04-21T13:26:28.885729+00:00"
  },
  "XOM": {
    "price": 147.68,
    "change_pct": 0.85,
    "name": "ExxonMobil",
    "_updated": "2026-04-21T13:26:28.886130+00:00"
  },
  "CVX": {
    "price": 183.25,
    "change_pct": -0.4,
    "name": "Chevron",
    "_updated": "2026-04-21T13:26:28.886565+00:00"
  },
  "LMT": {
    "price": 581.28,
    "change_pct": -1.84,
    "name": "Lockheed Martin",
    "_updated": "2026-04-21T13:26:28.886971+00:00"
  },
  "RTX": {
    "price": 195.79,
    "change_pct": -0.32,
    "name": "RTX Corp",
    "_updated": "2026-04-21T13:26:28.887372+00:00"
  },
  "NOC": {
    "price": 656.98,
    "change_pct": -1.24,
    "name": "Northrop Grumman",
    "_updated": "2026-04-21T13:26:28.887805+00:00"
  },
  "LLY": {
    "price": 919.9,
    "change_pct": -0.77,
    "name": "Eli Lilly",
    "_updated": "2026-04-21T13:26:28.888195+00:00"
  },
  "PFE": {
    "price": 27.52,
    "change_pct": -0.15,
    "name": "Pfizer",
    "_updated": "2026-04-21T13:26:28.888645+00:00"
  },
  "JNJ": {
    "price": 230.69,
    "change_pct": -1.49,
    "name": "Johnson & Johnson",
    "_updated": "2026-04-21T13:26:28.889047+00:00"
  },
  "BTC": {
    "price": 76111.99,
    "change_pct": 0.32,
    "name": "Bitcoin",
    "_updated": "2026-04-21T13:26:28.889438+00:00"
  },
  "ETH": {
    "price": 2309.91,
    "change_pct": -0.23,
    "name": "Ethereum",
    "_updated": "2026-04-21T13:26:28.889856+00:00"
  },
  "GLD": {
    "price": 442.09,
    "change_pct": -0.86,
    "name": "Gold ETF",
    "_updated": "2026-04-21T13:26:28.890242+00:00"
  },
  "TLT": {
    "price": 87.05,
    "change_pct": -0.02,
    "name": "20yr Treasury ETF",
    "_updated": "2026-04-21T13:26:28.890665+00:00"
  },
  "PLTR": {
    "price": 145.89,
    "change_pct": -0.34,
    "name": "Palantir",
    "_updated": "2026-04-21T13:26:28.891074+00:00"
  },
  "COIN": {
    "price": 211.63,
    "change_pct": 2.57,
    "name": "Coinbase",
    "_updated": "2026-04-21T13:26:28.891462+00:00"
  },
  "HRTX": {
    "price": 1.05,
    "change_pct": 5.0,
    "name": "HRTX",
    "_updated": "2026-04-21T13:26:28.891932+00:00"
  },
  "GD": {
    "price": 332.14,
    "change_pct": -1.23,
    "name": "General Dynamics",
    "_updated": "2026-04-21T13:26:28.892329+00:00"
  },
  "XRP": {
    "price": 1.43,
    "change_pct": 0.59,
    "name": "XRP Ripple",
    "_updated": "2026-04-21T13:26:28.892751+00:00"
  },
  "UNH": {
    "price": 323.48,
    "change_pct": -0.35,
    "name": "UnitedHealth Group",
    "_updated": "2026-04-21T13:26:28.893153+00:00"
  },
  "HCA": {
    "price": 478.13,
    "change_pct": -2.02,
    "name": "HCA Healthcare",
    "_updated": "2026-04-21T13:26:28.893565+00:00"
  },
  "CVS": {
    "price": 76.58,
    "change_pct": -0.93,
    "name": "CVS Health",
    "_updated": "2026-04-21T13:26:28.893957+00:00"
  }
}